.DS_Store
AssemblyTron/Copy Cloning.bat
AssemblyTron/Copy_Cloning.sh
AssemblyTron/Gibson.py
AssemblyTron/Update_Input.py
AssemblyTron/__init__.py
AssemblyTron/__main__.py
AssemblyTron/j5_to_csvs+digests.R
AssemblyTron/j5_to_csvs.R
AssemblyTron/j5_to_csvs.py
AssemblyTron/j5_to_csvs_digests.py
AssemblyTron/opentrons_demo_script.py
AssemblyTron/pathswriter.py
AssemblyTron/static_wired_IP_address.py
AssemblyTron/todaysdate.py
AssemblyTron/Cloning/IVA.py
AssemblyTron/Cloning/IVA_separatepcrruns_gradient-old.py
AssemblyTron/Cloning/IVA_separatepcrruns_gradient.py
AssemblyTron/Cloning/IVA_separatepcrruns_gradient_writer.py
AssemblyTron/Cloning/Setup.py
AssemblyTron/Cloning/Setup_seppcr_gradient_24 - Copy.py
AssemblyTron/Cloning/Setup_seppcr_gradient_24.py
AssemblyTron/Cloning/Setup_seppcr_gradient_96.py
AssemblyTron/Cloning/__init__.py
AssemblyTron/Cloning/dilution_24.py
AssemblyTron/Cloning/dilution_24_writer.py
AssemblyTron/Cloning/dilution_96.py
AssemblyTron/Cloning/dilution_96_writer.py
AssemblyTron/Cloning/j5_to_csvs.py
AssemblyTron/Error_prone_PCR_Golden_Gate/1_Setup_STD_GoldenGate_PCR.py
AssemblyTron/Error_prone_PCR_Golden_Gate/1_Setup_STD_GoldenGate_digests_PCR.py
AssemblyTron/Error_prone_PCR_Golden_Gate/Error_prone_PCR_writer.py
AssemblyTron/Error_prone_PCR_Golden_Gate/GoldenGate_digests_separatepcrruns_gradient_writer.py
AssemblyTron/Error_prone_PCR_Golden_Gate/GoldenGate_separatepcrruns_gradient_writer.py
AssemblyTron/Error_prone_PCR_Golden_Gate/Setup_Error_prone_PCR.py
AssemblyTron/Error_prone_PCR_Golden_Gate/Setup_Error_prone_PCR_NOdigest.py
AssemblyTron/Error_prone_PCR_Golden_Gate/Setup_STD_GoldenGate_Assembly.py
AssemblyTron/Error_prone_PCR_Golden_Gate/Setup_STD_GoldenGate_digests_Assembly.py
AssemblyTron/Error_prone_PCR_Golden_Gate/__init__.py
AssemblyTron/Error_prone_PCR_Golden_Gate/dilution_24_digests_writer.py
AssemblyTron/Error_prone_PCR_Golden_Gate/dilution_Error_prone_PCR_writer.py
AssemblyTron/Error_prone_PCR_Golden_Gate/j5_to_csvs.py
AssemblyTron-0.1.0.dist-info/LICENSE.txt
AssemblyTron-0.1.0.dist-info/METADATA
AssemblyTron-0.1.0.dist-info/WHEEL
AssemblyTron-0.1.0.dist-info/top_level.txt
AssemblyTron-0.1.0.dist-info/RECORD
