Metadata-Version: 2.1
Name: AssemblyTron
Version: 0.1.0
Summary: A package for automating DNA assembly with an Opentrons liquid handling robot
Home-page: https://github.com/PlantSynBioLab/opentrons
Author: John Bryant
Author-email: jbryant2@vt.edu
License: Apache License 2.0
Project-URL: Bug Tracker, https://github.com/pypa/sampleproject/issues
Classifier: Programming Language :: Python :: 3
Classifier: Operating System :: OS Independent
Classifier: License :: OSI Approved :: Apache Software License
Requires-Python: >=3.6
License-File: LICENSE.txt
Requires-Dist: pandas
Requires-Dist: numpy
Requires-Dist: datetime
